aakrab/__init__.py
aakrab/admin.py
aakrab/apps.py
aakrab/auth_hooks.py
aakrab/models.py
aakrab/tests.py
aakrab/urls.py
aakrab/utils.py
aakrab/views.py
aakrab/migrations/__init__.py
aakrab/templates/aakrab/base.html
aakrab/templates/aakrab/index.html
aa_krab-0.0.1.dist-info/LICENSE
aa_krab-0.0.1.dist-info/METADATA
aa_krab-0.0.1.dist-info/WHEEL
aa_krab-0.0.1.dist-info/top_level.txt
aa_krab-0.0.1.dist-info/RECORD
