Metadata-Version: 2.1
Name: aa-krab
Version: 0.0.1
Summary: A Wormhole Krab Fleet tracking system for Alliance Auth
Home-page: https://gitlab.com/hole-punchers/aa-krab
Author: Belial Morningstar
Author-email: jtrenaud1s@gmail.com
License: GPLv3
Platform: UNKNOWN
Classifier: Environment :: Web Environment
Classifier: Framework :: Django
Classifier: Framework :: Django :: 3.2
Classifier: Intended Audience :: Developers
Classifier: Operating System :: POSIX :: Linux
Classifier: Programming Language :: Python
Classifier: Programming Language :: Python :: 3.7
Classifier: Programming Language :: Python :: 3.8
Classifier: Programming Language :: Python :: 3.9
Classifier: License :: OSI Approved :: GNU General Public License v3 (GPLv3)
Classifier: Topic :: Internet :: WWW/HTTP
Classifier: Topic :: Internet :: WWW/HTTP :: Dynamic Content
Requires-Python: ~=3.8
License-File: LICENSE
Requires-Dist: allianceauth (>=2.11.0)
Requires-Dist: typing ; python_version=="3.8"
Provides-Extra: testing
